{
  "showbox.error.title": "Ошибка",
  "showbox.error.headertext": "Произошла ошибка",
  "exception.dirnotfound": "Папка %s не найдена",
  "error.configurecon.unabletocreatefile": "Невозможно создать файл %s",
  "error.unabletodelete.file": "Ошибка при удалении файла: %s",
  "error.create.remote.file": "Ошибка при создании файл на сервере: %s",
  "error.create.remote.dir": "Ошибка при создании директории на сервере: %s",
  "error.delete.remote.dir": "Ошибка при удалении директории на сервере: %s",
  "error.load.remote.file": "Ошибка при загрузке файла на сервер: %s",
  "error.connection.unsuccessful": "Ошибка при подключении: %s",
  "error.json.load": "Ошибка при создании json: %s",
  "error.json.value_list.unexp_open_char": "Не ожиданный открывающий символ",
  "error.json.exp_value": "Ожидалось значение",
  "error.json.exp_str": "Ожидалась строка",
  "error.json.value_list.exp_start_brace": "Ожидалась открывающая фигурная скобка",
  "error.json.unexp_char": "Не ожиданный символ",
  "error.json.change.text": "Неудачное преобразование текста json: %s",
  "error.json.value.unexp_end": "Не ожиданный конец",
  "error.json.value.array_expected": "Ожидался массив",
  "error.json.value_list.undefined_entry": "Не определенная запись",
  "error.interpreter.exp_start_char_str": "Ожидался начальный символ строки [\"]",
  "error.interpreter.exp_start_num": "Ожидалось начало числа",
  "error.interpreter.exp_num_after_dot": "Ожидалось число после точки",
  "erroe.interpreter.exp_num": "Ожидалось число",
  "text.withoutextention": "Без разрешения",
  "text.enter": "Введите %s",
  "unsuccess": "Неудачно",
  "hostname": "Имя хоста",
  "ok": "Ок",
  "number": "Число",
  "port": "Порт",
  "name": "Имя",
  "value": "Значение",
  "username": "Имя пользователя",
  "password": "Пароль",
  "filename": "Имя файла",
  "configure": "Конфигурация",
  "dirname": "Имя дирректории",
  "success": "Успешно",
  "delete": "Удалить",
  "in_index": "по индексу",
  "button.save": "Сохранить",
  "button.cancel": "Отмена",
  "button.check.connection": "Проверить соединение",
  "success.file.created": "Файл успешно создан",
  "succes.file.deleted": "Файл успешно удален",
  "unsucces.file.delete": "Файл не был удален",
  "menu.language": "Язык",
  "menu.file": "Файл",
  "menu.connect": "Соединение",
  "menu.info": "Информация",
  "menu.view": "Вид",
  "menu_item.view.text_equivalent": "Текстовый эквивалент",
  "connection.success": "Подключение прошло успешно",
  "connection.unsuccessful": "Подключение не удалось",
  "error.input.notentered": "Вы не ввели %s",
  "menu_item.open.local": "Открыть",
  "menu_item.configure": "Кофигурация",
  "menu_item.exit.global": "Выйти из программы",
  "menu_item.exit.file": "Закрыть файл",
  "menu_item.exit.folder": "Закрыть папку",
  "menu_item.open.local.folder": "Открыть локальную папку",
  "menu_item.open.remote.folder": "Открыть удаленную папку",
  "menu_item.disconnect": "Отключиться",
  "menu_item.delete.json": "Удалить JSON файл",
  "menu_item.create.json": "Создать JSON файл",
  "menu_item.save.file": "Сохранить файл",
  "menu_item.save.as": "Сохранить как",
  "menu_item.create.directory": "Создать директорию",
  "menu_item.delete.directory": "Удалить директорию",
  "menu_item.information.about.this.app": "Информация о приложении",
  "menu_item.information.guide": "Инструкция по использованию",
  "context_menu.add_unit": "Добавить элемент",
  "context_menu.add_unit_list": "Добавить список элементов",
  "context_menu.add_array_list": "Добавить массив",
  "unit.new_unit": "Новый элемент",
  "unit.new_unit_list": "новый список элементов",
  "unit.new_array_list": "новый массив"
}
